bigarray/__init__.py
bigarray/mmap_array.py
bigarray/pointer_array.py
tests/__init__.py
tests/test_mmaparray.py
tests/test_pointerarray.py
bigarray-0.2.2.dist-info/LICENSE
bigarray-0.2.2.dist-info/METADATA
bigarray-0.2.2.dist-info/WHEEL
bigarray-0.2.2.dist-info/top_level.txt
bigarray-0.2.2.dist-info/RECORD
